[{"Activity": "Cash", "Description": "Cash and Cash Equivalents", "Category": "Assets", "Subcategory": "Current Assets", "FYE": "7,264,372", "BS_id": 1, "school": "advantage", "total_sum1": 67784.6499999998, "total_sum2": -235948.73000000013, "total_sum3": -5282.220000000028, "total_sum4": -17606.109999999924, "total_sum5": 151355.63999999975, "total_sum6": 244391.94999999995, "total_sum7": 287343.1799999999, "total_sum8": -389154.64, "total_sum9": 20924.659999999654, "total_sum10": -168930.44999999995, "total_sum11": -241677.12999999998, "total_sum12": 231460.57000000004}, {"Activity": "Cash", "Description": "Cash and Cash Equivalents", "Category": "Assets", "Subcategory": "Current Assets", "FYE": "3,900,721", "BS_id": 1, "school": "village-tech", "total_sum1": 67784.6499999998, "total_sum2": -235948.73000000013, "total_sum3": -5282.220000000028, "total_sum4": -17606.109999999924, "total_sum5": 151355.63999999975, "total_sum6": 244391.94999999995, "total_sum7": 287343.1799999999, "total_sum8": -389154.64, "total_sum9": 20924.659999999654, "total_sum10": -168930.44999999995, "total_sum11": -241677.12999999998, "total_sum12": 231460.57000000004, "difference_9": "$3,921,646", "difference_10": "$3,752,715", "difference_11": "$3,511,038", "difference_12": "$3,742,499", "difference_1": "$3,810,283", "difference_2": "$3,574,335", "difference_3": "$3,569,052", "difference_4": "$3,551,446", "difference_5": "$3,702,802", "difference_6": "$3,947,194", "difference_7": "$4,234,537", "difference_8": "$3,845,382", "fytd": "$(55,339)", "debt_9": "$3,879,796", "debt_10": "$4,048,727", "debt_11": "$4,290,404", "debt_12": "$4,058,943", "debt_1": "$3,991,159", "debt_2": "$4,227,107", "debt_3": "$4,232,390", "debt_4": "$4,249,996", "debt_5": "$4,098,640", "debt_6": "$3,854,248", "debt_7": "$3,566,905", "debt_8": "$3,956,060", "debt_fytd": "$(55,339)", "net_assets9": "3,435,770", "net_assets10": "3,279,591", "net_assets11": "3,272,341", "net_assets12": "3,281,747", "net_assets1": "3,311,596", "net_assets2": "3,313,251", "net_assets3": "3,289,057", "net_assets4": "3,288,088", "net_assets5": "3,464,720", "net_assets6": "3,604,326", "net_assets7": "3,789,964", "net_assets8": "3,331,546"}, {"Activity": "Cash", "Description": "Cash and Cash Equivalents", "Category": "Assets", "Subcategory": "Current Assets", "FYE": "7,436,462", "BS_id": 1, "school": "prepschool", "total_sum1": 67784.6499999998, "total_sum2": -235948.73000000013, "total_sum3": -5282.220000000028, "total_sum4": -17606.109999999924, "total_sum5": 151355.63999999975, "total_sum6": 244391.94999999995, "total_sum7": 287343.1799999999, "total_sum8": -389154.64, "total_sum9": 20924.659999999654, "total_sum10": -168930.44999999995, "total_sum11": -241677.12999999998, "total_sum12": 231460.57000000004}, {"Activity": "Cash", "Description": "Cash and Cash Equivalents", "Category": "Assets", "Subcategory": "Current Assets", "FYE": "9,437,238", "BS_id": 1, "school": "cumberland", "total_sum1": 67784.6499999998, "total_sum2": -235948.73000000013, "total_sum3": -5282.220000000028, "total_sum4": -17606.109999999924, "total_sum5": 151355.63999999975, "total_sum6": 244391.94999999995, "total_sum7": 287343.1799999999, "total_sum8": -389154.64, "total_sum9": 20924.659999999654, "total_sum10": -168930.44999999995, "total_sum11": -241677.12999999998, "total_sum12": 231460.57000000004}, {"Activity": "Cash", "Description": "Cash and Cash Equivalents", "Category": "Assets", "Subcategory": "Current Assets", "FYE": "918,161", "BS_id": 1, "school": "manara", "total_sum1": 67784.6499999998, "total_sum2": -235948.73000000013, "total_sum3": -5282.220000000028, "total_sum4": -17606.109999999924, "total_sum5": 151355.63999999975, "total_sum6": 244391.94999999995, "total_sum7": 287343.1799999999, "total_sum8": -389154.64, "total_sum9": 20924.659999999654, "total_sum10": -168930.44999999995, "total_sum11": -241677.12999999998, "total_sum12": 231460.57000000004}, {"Activity": "Restr", "Description": "Restricted Cash (Bonds)", "Category": "Assets", "Subcategory": "Current Assets", "FYE": "495,394", "BS_id": 2, "school": "advantage", "total_sum1": -28.360000000000582, "total_sum2": 16229.130000000001, "total_sum3": -10465.8, "total_sum4": -3785.8999999999983, "total_sum5": -24658.77, "total_sum6": -3613.219999999999, "total_sum7": -669.93, "total_sum8": 673.0, "total_sum9": -35130.83, "total_sum10": -11862.019999999997, "total_sum11": -3083.830000000001, "total_sum12": 6997.039999999998}, {"Activity": "Restr", "Description": "Restricted Cash (Bonds)", "Category": "Assets", "Subcategory": "Current Assets", "FYE": "", "BS_id": 2, "school": "cumberland", "total_sum1": -28.360000000000582, "total_sum2": 16229.130000000001, "total_sum3": -10465.8, "total_sum4": -3785.8999999999983, "total_sum5": -24658.77, "total_sum6": -3613.219999999999, "total_sum7": -669.93, "total_sum8": 673.0, "total_sum9": -35130.83, "total_sum10": -11862.019999999997, "total_sum11": -3083.830000000001, "total_sum12": 6997.039999999998}, {"Activity": "Restr", "Description": "Restricted Cash (Bonds)", "Category": "Assets", "Subcategory": "Current Assets", "FYE": "1,525,397", "BS_id": 2, "school": "village-tech", "total_sum1": -28.360000000000582, "total_sum2": 16229.130000000001, "total_sum3": -10465.8, "total_sum4": -3785.8999999999983, "total_sum5": -24658.77, "total_sum6": -3613.219999999999, "total_sum7": -669.93, "total_sum8": 673.0, "total_sum9": -35130.83, "total_sum10": -11862.019999999997, "total_sum11": -3083.830000000001, "total_sum12": 6997.039999999998, "difference_9": "$1,490,266", "difference_10": "$1,478,404", "difference_11": "$1,475,320", "difference_12": "$1,482,317", "difference_1": "$1,482,289", "difference_2": "$1,498,518", "difference_3": "$1,488,052", "difference_4": "$1,484,266", "difference_5": "$1,459,608", "difference_6": "$1,455,994", "difference_7": "$1,455,325", "difference_8": "$1,455,998", "fytd": "$(69,399)", "debt_9": "$1,560,528", "debt_10": "$1,572,390", "debt_11": "$1,575,474", "debt_12": "$1,568,477", "debt_1": "$1,568,505", "debt_2": "$1,552,276", "debt_3": "$1,562,742", "debt_4": "$1,566,528", "debt_5": "$1,591,186", "debt_6": "$1,594,800", "debt_7": "$1,595,469", "debt_8": "$1,594,796", "debt_fytd": "$(69,399)", "net_assets9": "1,060,446", "net_assets10": "904,267", "net_assets11": "897,017", "net_assets12": "906,423", "net_assets1": "936,272", "net_assets2": "937,927", "net_assets3": "913,733", "net_assets4": "912,764", "net_assets5": "1,089,396", "net_assets6": "1,229,002", "net_assets7": "1,414,640", "net_assets8": "956,222"}, {"Activity": "Restr", "Description": "Restricted Cash (Bonds)", "Category": "Assets", "Subcategory": "Current Assets", "FYE": "", "BS_id": 2, "school": "manara", "total_sum1": -28.360000000000582, "total_sum2": 16229.130000000001, "total_sum3": -10465.8, "total_sum4": -3785.8999999999983, "total_sum5": -24658.77, "total_sum6": -3613.219999999999, "total_sum7": -669.93, "total_sum8": 673.0, "total_sum9": -35130.83, "total_sum10": -11862.019999999997, "total_sum11": -3083.830000000001, "total_sum12": 6997.039999999998}, {"Activity": "Restr", "Description": "Restricted Cash (Bonds)", "Category": "Assets", "Subcategory": "Current Assets", "FYE": "204", "BS_id": 2, "school": "prepschool", "total_sum1": -28.360000000000582, "total_sum2": 16229.130000000001, "total_sum3": -10465.8, "total_sum4": -3785.8999999999983, "total_sum5": -24658.77, "total_sum6": -3613.219999999999, "total_sum7": -669.93, "total_sum8": 673.0, "total_sum9": -35130.83, "total_sum10": -11862.019999999997, "total_sum11": -3083.830000000001, "total_sum12": 6997.039999999998}, {"Activity": "DFS+F", "Description": "Due from State (FSP and Federal)", "Category": "Assets", "Subcategory": "Current Assets", "FYE": "2,516,007", "BS_id": 3, "school": "advantage", "total_sum1": 0, "total_sum2": 110746.43000000001, "total_sum3": 13589.130000000005, "total_sum4": 48918.42, "total_sum5": 27203.699999999986, "total_sum6": -54523.55000000001, "total_sum7": -91893.33999999998, "total_sum8": 0, "total_sum9": -699383.6000000001, "total_sum10": 0, "total_sum11": 156356.21, "total_sum12": -71367.31000000001}, {"Activity": "DFS+F", "Description": "Due from State (FSP and Federal)", "Category": "Assets", "Subcategory": "Current Assets", "FYE": "2,024,696", "BS_id": 3, "school": "cumberland", "total_sum1": 0, "total_sum2": 110746.43000000001, "total_sum3": 13589.130000000005, "total_sum4": 48918.42, "total_sum5": 27203.699999999986, "total_sum6": -54523.55000000001, "total_sum7": -91893.33999999998, "total_sum8": 0, "total_sum9": -699383.6000000001, "total_sum10": 0, "total_sum11": 156356.21, "total_sum12": -71367.31000000001}, {"Activity": "DFS+F", "Description": "Due from State (FSP and Federal)", "Category": "Assets", "Subcategory": "Current Assets", "FYE": "1,624,099", "BS_id": 3, "school": "village-tech", "total_sum1": 0, "total_sum2": 110746.43000000001, "total_sum3": 13589.130000000005, "total_sum4": 48918.42, "total_sum5": 27203.699999999986, "total_sum6": -54523.55000000001, "total_sum7": -91893.33999999998, "total_sum8": 0, "total_sum9": -699383.6000000001, "total_sum10": 0, "total_sum11": 156356.21, "total_sum12": -71367.31000000001, "difference_9": "$924,715", "difference_10": "$924,715", "difference_11": "$1,081,072", "difference_12": "$1,009,704", "difference_1": "$1,009,704", "difference_2": "$1,120,451", "difference_3": "$1,134,040", "difference_4": "$1,182,958", "difference_5": "$1,210,162", "difference_6": "$1,155,638", "difference_7": "$1,063,745", "difference_8": "$1,063,745", "fytd": "$(560,354)", "debt_9": "$2,323,483", "debt_10": "$2,323,483", "debt_11": "$2,167,126", "debt_12": "$2,238,494", "debt_1": "$2,238,494", "debt_2": "$2,127,747", "debt_3": "$2,114,158", "debt_4": "$2,065,240", "debt_5": "$2,038,036", "debt_6": "$2,092,560", "debt_7": "$2,184,453", "debt_8": "$2,184,453", "debt_fytd": "$(560,354)", "net_assets9": "1,159,148", "net_assets10": "1,002,969", "net_assets11": "995,719", "net_assets12": "1,005,125", "net_assets1": "1,034,974", "net_assets2": "1,036,629", "net_assets3": "1,012,435", "net_assets4": "1,011,466", "net_assets5": "1,188,098", "net_assets6": "1,327,704", "net_assets7": "1,513,342", "net_assets8": "1,054,924"}, {"Activity": "DFS+F", "Description": "Due from State (FSP and Federal)", "Category": "Assets", "Subcategory": "Current Assets", "FYE": "2,078,981", "BS_id": 3, "school": "prepschool", "total_sum1": 0, "total_sum2": 110746.43000000001, "total_sum3": 13589.130000000005, "total_sum4": 48918.42, "total_sum5": 27203.699999999986, "total_sum6": -54523.55000000001, "total_sum7": -91893.33999999998, "total_sum8": 0, "total_sum9": -699383.6000000001, "total_sum10": 0, "total_sum11": 156356.21, "total_sum12": -71367.31000000001}, {"Activity": "DFS+F", "Description": "Due from State (FSP and Federal)", "Category": "Assets", "Subcategory": "Current Assets", "FYE": "868,254", "BS_id": 3, "school": "manara", "total_sum1": 0, "total_sum2": 110746.43000000001, "total_sum3": 13589.130000000005, "total_sum4": 48918.42, "total_sum5": 27203.699999999986, "total_sum6": -54523.55000000001, "total_sum7": -91893.33999999998, "total_sum8": 0, "total_sum9": -699383.6000000001, "total_sum10": 0, "total_sum11": 156356.21, "total_sum12": -71367.31000000001}, {"Activity": "OTHR", "Description": "Pledges and Other Receivables", "Category": "Assets", "Subcategory": "Current Assets", "FYE": "69", "BS_id": 4, "school": "advantage", "total_sum1": 0, "total_sum2": 0, "total_sum3": 0, "total_sum4": 0, "total_sum5": 0, "total_sum6": 0, "total_sum7": 0, "total_sum8": 0, "total_sum9": 0, "total_sum10": 0, "total_sum11": 0, "total_sum12": 0}, {"Activity": "OTHR", "Description": "Pledges and Other Receivables", "Category": "Assets", "Subcategory": "Current Assets", "FYE": "20,507", "BS_id": 4, "school": "cumberland", "total_sum1": 0, "total_sum2": 0, "total_sum3": 0, "total_sum4": 0, "total_sum5": 0, "total_sum6": 0, "total_sum7": 0, "total_sum8": 0, "total_sum9": 0, "total_sum10": 0, "total_sum11": 0, "total_sum12": 0}, {"Activity": "OTHR", "Description": "Pledges and Other Receivables", "Category": "Assets", "Subcategory": "Current Assets", "FYE": "", "BS_id": 4, "school": "prepschool", "total_sum1": 0, "total_sum2": 0, "total_sum3": 0, "total_sum4": 0, "total_sum5": 0, "total_sum6": 0, "total_sum7": 0, "total_sum8": 0, "total_sum9": 0, "total_sum10": 0, "total_sum11": 0, "total_sum12": 0}, {"Activity": "OTHR", "Description": "Pledges and Other Receivables", "Category": "Assets", "Subcategory": "Current Assets", "FYE": "", "BS_id": 4, "school": "village-tech", "total_sum1": 0, "total_sum2": 0, "total_sum3": 0, "total_sum4": 0, "total_sum5": 0, "total_sum6": 0, "total_sum7": 0, "total_sum8": 0, "total_sum9": 0, "total_sum10": 0, "total_sum11": 0, "total_sum12": 0, "difference_9": "", "difference_10": "", "difference_11": "", "difference_12": "", "difference_1": "", "difference_2": "", "difference_3": "", "difference_4": "", "difference_5": "", "difference_6": "", "difference_7": "", "difference_8": "", "fytd": "", "debt_9": "", "debt_10": "", "debt_11": "", "debt_12": "", "debt_1": "", "debt_2": "", "debt_3": "", "debt_4": "", "debt_5": "", "debt_6": "", "debt_7": "", "debt_8": "", "debt_fytd": "", "net_assets9": "(464,951)", "net_assets10": "(621,130)", "net_assets11": "(628,380)", "net_assets12": "(618,974)", "net_assets1": "(589,125)", "net_assets2": "(587,470)", "net_assets3": "(611,664)", "net_assets4": "(612,633)", "net_assets5": "(436,001)", "net_assets6": "(296,395)", "net_assets7": "(110,757)", "net_assets8": "(569,175)"}, {"Activity": "OTHR", "Description": "Pledges and Other Receivables", "Category": "Assets", "Subcategory": "Current Assets", "FYE": "", "BS_id": 4, "school": "manara", "total_sum1": 0, "total_sum2": 0, "total_sum3": 0, "total_sum4": 0, "total_sum5": 0, "total_sum6": 0, "total_sum7": 0, "total_sum8": 0, "total_sum9": 0, "total_sum10": 0, "total_sum11": 0, "total_sum12": 0}, {"Activity": "Inventory", "Description": "Inventory", "Category": "Assets", "Subcategory": "Current Assets", "FYE": "30,945", "BS_id": 5, "school": "advantage", "total_sum1": 0, "total_sum2": 0, "total_sum3": 0, "total_sum4": 0, "total_sum5": 0, "total_sum6": 0, "total_sum7": 0, "total_sum8": 0, "total_sum9": 0, "total_sum10": 0, "total_sum11": 0, "total_sum12": 0}, {"Activity": "Inventory", "Description": "Inventory", "Category": "Assets", "Subcategory": "Current Assets", "FYE": "", "BS_id": 5, "school": "cumberland", "total_sum1": 0, "total_sum2": 0, "total_sum3": 0, "total_sum4": 0, "total_sum5": 0, "total_sum6": 0, "total_sum7": 0, "total_sum8": 0, "total_sum9": 0, "total_sum10": 0, "total_sum11": 0, "total_sum12": 0}, {"Activity": "Inventory", "Description": "Inventory", "Category": "Assets", "Subcategory": "Current Assets", "FYE": "", "BS_id": 5, "school": "prepschool", "total_sum1": 0, "total_sum2": 0, "total_sum3": 0, "total_sum4": 0, "total_sum5": 0, "total_sum6": 0, "total_sum7": 0, "total_sum8": 0, "total_sum9": 0, "total_sum10": 0, "total_sum11": 0, "total_sum12": 0}, {"Activity": "Inventory", "Description": "Inventory", "Category": "Assets", "Subcategory": "Current Assets", "FYE": "", "BS_id": 5, "school": "village-tech", "total_sum1": 0, "total_sum2": 0, "total_sum3": 0, "total_sum4": 0, "total_sum5": 0, "total_sum6": 0, "total_sum7": 0, "total_sum8": 0, "total_sum9": 0, "total_sum10": 0, "total_sum11": 0, "total_sum12": 0, "difference_9": "", "difference_10": "", "difference_11": "", "difference_12": "", "difference_1": "", "difference_2": "", "difference_3": "", "difference_4": "", "difference_5": "", "difference_6": "", "difference_7": "", "difference_8": "", "fytd": "", "debt_9": "", "debt_10": "", "debt_11": "", "debt_12": "", "debt_1": "", "debt_2": "", "debt_3": "", "debt_4": "", "debt_5": "", "debt_6": "", "debt_7": "", "debt_8": "", "debt_fytd": "", "net_assets9": "(464,951)", "net_assets10": "(621,130)", "net_assets11": "(628,380)", "net_assets12": "(618,974)", "net_assets1": "(589,125)", "net_assets2": "(587,470)", "net_assets3": "(611,664)", "net_assets4": "(612,633)", "net_assets5": "(436,001)", "net_assets6": "(296,395)", "net_assets7": "(110,757)", "net_assets8": "(569,175)"}, {"Activity": "Inventory", "Description": "Inventory", "Category": "Assets", "Subcategory": "Current Assets", "FYE": "", "BS_id": 5, "school": "manara", "total_sum1": 0, "total_sum2": 0, "total_sum3": 0, "total_sum4": 0, "total_sum5": 0, "total_sum6": 0, "total_sum7": 0, "total_sum8": 0, "total_sum9": 0, "total_sum10": 0, "total_sum11": 0, "total_sum12": 0}, {"Activity": "PPD", "Description": "Prepaid Expenses", "Category": "Assets", "Subcategory": "Current Assets", "FYE": "", "BS_id": 6, "school": "advantage", "total_sum1": 0, "total_sum2": 0, "total_sum3": 0, "total_sum4": 0, "total_sum5": 0, "total_sum6": 0, "total_sum7": 0, "total_sum8": 0, "total_sum9": 0, "total_sum10": 0, "total_sum11": 0, "total_sum12": 0}, {"Activity": "PPD", "Description": "Prepaid Expenses", "Category": "Assets", "Subcategory": "Current Assets", "FYE": "175,142", "BS_id": 6, "school": "prepschool", "total_sum1": 0, "total_sum2": 0, "total_sum3": 0, "total_sum4": 0, "total_sum5": 0, "total_sum6": 0, "total_sum7": 0, "total_sum8": 0, "total_sum9": 0, "total_sum10": 0, "total_sum11": 0, "total_sum12": 0}, {"Activity": "PPD", "Description": "Prepaid Expenses", "Category": "Assets", "Subcategory": "Current Assets", "FYE": "42,507", "BS_id": 6, "school": "cumberland", "total_sum1": 0, "total_sum2": 0, "total_sum3": 0, "total_sum4": 0, "total_sum5": 0, "total_sum6": 0, "total_sum7": 0, "total_sum8": 0, "total_sum9": 0, "total_sum10": 0, "total_sum11": 0, "total_sum12": 0}, {"Activity": "PPD", "Description": "Prepaid Expenses", "Category": "Assets", "Subcategory": "Current Assets", "FYE": "41,397", "BS_id": 6, "school": "village-tech", "total_sum1": 0, "total_sum2": 0, "total_sum3": 0, "total_sum4": 0, "total_sum5": 0, "total_sum6": 0, "total_sum7": 0, "total_sum8": 0, "total_sum9": 0, "total_sum10": 0, "total_sum11": 0, "total_sum12": 0, "difference_9": "$41,397", "difference_10": "$41,397", "difference_11": "$41,397", "difference_12": "$41,397", "difference_1": "$41,397", "difference_2": "$41,397", "difference_3": "$41,397", "difference_4": "$41,397", "difference_5": "$41,397", "difference_6": "$41,397", "difference_7": "$41,397", "difference_8": "$41,397", "fytd": "", "debt_9": "$41,397", "debt_10": "$41,397", "debt_11": "$41,397", "debt_12": "$41,397", "debt_1": "$41,397", "debt_2": "$41,397", "debt_3": "$41,397", "debt_4": "$41,397", "debt_5": "$41,397", "debt_6": "$41,397", "debt_7": "$41,397", "debt_8": "$41,397", "debt_fytd": "", "net_assets9": "(423,554)", "net_assets10": "(579,733)", "net_assets11": "(586,983)", "net_assets12": "(577,577)", "net_assets1": "(547,728)", "net_assets2": "(546,073)", "net_assets3": "(570,267)", "net_assets4": "(571,236)", "net_assets5": "(394,604)", "net_assets6": "(254,998)", "net_assets7": "(69,360)", "net_assets8": "(527,778)"}, {"Activity": "PPD", "Description": "Prepaid Expenses", "Category": "Assets", "Subcategory": "Current Assets", "FYE": "11,650", "BS_id": 6, "school": "manara", "total_sum1": 0, "total_sum2": 0, "total_sum3": 0, "total_sum4": 0, "total_sum5": 0, "total_sum6": 0, "total_sum7": 0, "total_sum8": 0, "total_sum9": 0, "total_sum10": 0, "total_sum11": 0, "total_sum12": 0}, {"Activity": "FA-L", "Description": "Land", "Category": "Assets", "Subcategory": "Capital Assets, Net", "FYE": "4,362,269", "BS_id": 7, "school": "advantage", "total_sum1": 0, "total_sum2": 0, "total_sum3": 0, "total_sum4": 0, "total_sum5": 0, "total_sum6": 0, "total_sum7": 0, "total_sum8": 0, "total_sum9": 0, "total_sum10": 0, "total_sum11": 0, "total_sum12": 0}, {"Activity": "FA-L", "Description": "Land", "Category": "Assets", "Subcategory": "Capital Assets, Net", "FYE": "2,444,593", "BS_id": 7, "school": "prepschool", "total_sum1": 0, "total_sum2": 0, "total_sum3": 0, "total_sum4": 0, "total_sum5": 0, "total_sum6": 0, "total_sum7": 0, "total_sum8": 0, "total_sum9": 0, "total_sum10": 0, "total_sum11": 0, "total_sum12": 0}, {"Activity": "FA-L", "Description": "Land", "Category": "Assets", "Subcategory": "Capital Assets, Net", "FYE": "4,616,639", "BS_id": 7, "school": "cumberland", "total_sum1": 0, "total_sum2": 0, "total_sum3": 0, "total_sum4": 0, "total_sum5": 0, "total_sum6": 0, "total_sum7": 0, "total_sum8": 0, "total_sum9": 0, "total_sum10": 0, "total_sum11": 0, "total_sum12": 0}, {"Activity": "FA-L", "Description": "Land", "Category": "Assets", "Subcategory": "Capital Assets, Net", "FYE": "2,077,145", "BS_id": 7, "school": "village-tech", "total_sum1": 0, "total_sum2": 0, "total_sum3": 0, "total_sum4": 0, "total_sum5": 0, "total_sum6": 0, "total_sum7": 0, "total_sum8": 0, "total_sum9": 0, "total_sum10": 0, "total_sum11": 0, "total_sum12": 0, "difference_9": "$2,077,145", "difference_10": "$2,077,145", "difference_11": "$2,077,145", "difference_12": "$2,077,145", "difference_1": "$2,077,145", "difference_2": "$2,077,145", "difference_3": "$2,077,145", "difference_4": "$2,077,145", "difference_5": "$2,077,145", "difference_6": "$2,077,145", "difference_7": "$2,077,145", "difference_8": "$2,077,145", "fytd": "", "debt_9": "$2,077,145", "debt_10": "$2,077,145", "debt_11": "$2,077,145", "debt_12": "$2,077,145", "debt_1": "$2,077,145", "debt_2": "$2,077,145", "debt_3": "$2,077,145", "debt_4": "$2,077,145", "debt_5": "$2,077,145", "debt_6": "$2,077,145", "debt_7": "$2,077,145", "debt_8": "$2,077,145", "debt_fytd": "", "net_assets9": "1,612,194", "net_assets10": "1,456,015", "net_assets11": "1,448,765", "net_assets12": "1,458,171", "net_assets1": "1,488,020", "net_assets2": "1,489,675", "net_assets3": "1,465,481", "net_assets4": "1,464,512", "net_assets5": "1,641,144", "net_assets6": "1,780,750", "net_assets7": "1,966,388", "net_assets8": "1,507,970"}, {"Activity": "FA-L", "Description": "Land", "Category": "Assets", "Subcategory": "Capital Assets, Net", "FYE": "1,045,440", "BS_id": 7, "school": "manara", "total_sum1": 0, "total_sum2": 0, "total_sum3": 0, "total_sum4": 0, "total_sum5": 0, "total_sum6": 0, "total_sum7": 0, "total_sum8": 0, "total_sum9": 0, "total_sum10": 0, "total_sum11": 0, "total_sum12": 0}, {"Activity": "FA-BFE", "Description": "Building & Equipment", "Category": "Assets", "Subcategory": "Capital Assets, Net", "FYE": "31,764,190", "BS_id": 8, "school": "advantage", "total_sum1": 0, "total_sum2": 0, "total_sum3": 0, "total_sum4": 0, "total_sum5": 0, "total_sum6": 0, "total_sum7": 0, "total_sum8": 107.96, "total_sum9": 113750.0, "total_sum10": 146250.0, "total_sum11": 0, "total_sum12": 0}, {"Activity": "FA-BFE", "Description": "Building & Equipment", "Category": "Assets", "Subcategory": "Capital Assets, Net", "FYE": "15,402,459", "BS_id": 8, "school": "prepschool", "total_sum1": 0, "total_sum2": 0, "total_sum3": 0, "total_sum4": 0, "total_sum5": 0, "total_sum6": 0, "total_sum7": 0, "total_sum8": 107.96, "total_sum9": 113750.0, "total_sum10": 146250.0, "total_sum11": 0, "total_sum12": 0}, {"Activity": "FA-BFE", "Description": "Building & Equipment", "Category": "Assets", "Subcategory": "Capital Assets, Net", "FYE": "80,912,676", "BS_id": 8, "school": "cumberland", "total_sum1": 0, "total_sum2": 0, "total_sum3": 0, "total_sum4": 0, "total_sum5": 0, "total_sum6": 0, "total_sum7": 0, "total_sum8": 107.96, "total_sum9": 113750.0, "total_sum10": 146250.0, "total_sum11": 0, "total_sum12": 0}, {"Activity": "FA-BFE", "Description": "Building & Equipment", "Category": "Assets", "Subcategory": "Capital Assets, Net", "FYE": "23,116,972", "BS_id": 8, "school": "village-tech", "total_sum1": 0, "total_sum2": 0, "total_sum3": 0, "total_sum4": 0, "total_sum5": 0, "total_sum6": 0, "total_sum7": 0, "total_sum8": 107.96, "total_sum9": 113750.0, "total_sum10": 146250.0, "total_sum11": 0, "total_sum12": 0, "difference_9": "$23,230,722", "difference_10": "$23,376,972", "difference_11": "$23,376,972", "difference_12": "$23,376,972", "difference_1": "$23,376,972", "difference_2": "$23,376,972", "difference_3": "$23,376,972", "difference_4": "$23,376,972", "difference_5": "$23,376,972", "difference_6": "$23,376,972", "difference_7": "$23,376,972", "difference_8": "$23,377,080", "fytd": "$260,108", "debt_9": "$23,003,222", "debt_10": "$22,856,972", "debt_11": "$22,856,972", "debt_12": "$22,856,972", "debt_1": "$22,856,972", "debt_2": "$22,856,972", "debt_3": "$22,856,972", "debt_4": "$22,856,972", "debt_5": "$22,856,972", "debt_6": "$22,856,972", "debt_7": "$22,856,972", "debt_8": "$22,856,864", "debt_fytd": "$260,108", "net_assets9": "22,652,021", "net_assets10": "22,495,842", "net_assets11": "22,488,592", "net_assets12": "22,497,998", "net_assets1": "22,527,847", "net_assets2": "22,529,502", "net_assets3": "22,505,308", "net_assets4": "22,504,339", "net_assets5": "22,680,971", "net_assets6": "22,820,577", "net_assets7": "23,006,215", "net_assets8": "22,547,797"}, {"Activity": "FA-BFE", "Description": "Building & Equipment", "Category": "Assets", "Subcategory": "Capital Assets, Net", "FYE": "4,312,966", "BS_id": 8, "school": "manara", "total_sum1": 0, "total_sum2": 0, "total_sum3": 0, "total_sum4": 0, "total_sum5": 0, "total_sum6": 0, "total_sum7": 0, "total_sum8": 107.96, "total_sum9": 113750.0, "total_sum10": 146250.0, "total_sum11": 0, "total_sum12": 0}, {"Activity": "FA-AD", "Description": "Accumulated Depreciation", "Category": "Assets", "Subcategory": "Capital Assets, Net", "FYE": "(12,211,786)", "BS_id": 9, "school": "advantage", "total_sum1": 0, "total_sum2": -203937.28, "total_sum3": -66959.07999999999, "total_sum4": -63272.0, "total_sum5": -63272.0, "total_sum6": -53272.0, "total_sum7": -63272.0, "total_sum8": 0, "total_sum9": -62219.82, "total_sum10": -62219.82, "total_sum11": 0, "total_sum12": 0}, {"Activity": "FA-AD", "Description": "Accumulated Depreciation", "Category": "Assets", "Subcategory": "Capital Assets, Net", "FYE": "(3,128,878)", "BS_id": 9, "school": "prepschool", "total_sum1": 0, "total_sum2": -203937.28, "total_sum3": -66959.07999999999, "total_sum4": -63272.0, "total_sum5": -63272.0, "total_sum6": -53272.0, "total_sum7": -63272.0, "total_sum8": 0, "total_sum9": -62219.82, "total_sum10": -62219.82, "total_sum11": 0, "total_sum12": 0}, {"Activity": "FA-AD", "Description": "Accumulated Depreciation", "Category": "Assets", "Subcategory": "Capital Assets, Net", "FYE": "(12,784,291)", "BS_id": 9, "school": "cumberland", "total_sum1": 0, "total_sum2": -203937.28, "total_sum3": -66959.07999999999, "total_sum4": -63272.0, "total_sum5": -63272.0, "total_sum6": -53272.0, "total_sum7": -63272.0, "total_sum8": 0, "total_sum9": -62219.82, "total_sum10": -62219.82, "total_sum11": 0, "total_sum12": 0}, {"Activity": "FA-AD", "Description": "Accumulated Depreciation", "Category": "Assets", "Subcategory": "Capital Assets, Net", "FYE": "", "BS_id": 9, "school": "village-tech", "total_sum1": 0, "total_sum2": -203937.28, "total_sum3": -66959.07999999999, "total_sum4": -63272.0, "total_sum5": -63272.0, "total_sum6": -53272.0, "total_sum7": -63272.0, "total_sum8": 0, "total_sum9": -62219.82, "total_sum10": -62219.82, "total_sum11": 0, "total_sum12": 0, "difference_9": "$(62,220)", "difference_10": "$(124,440)", "difference_11": "$(124,440)", "difference_12": "$(124,440)", "difference_1": "$(124,440)", "difference_2": "$(328,377)", "difference_3": "$(395,336)", "difference_4": "$(458,608)", "difference_5": "$(521,880)", "difference_6": "$(575,152)", "difference_7": "$(638,424)", "difference_8": "$(638,424)", "fytd": "$(638,424)", "debt_9": "$62,220", "debt_10": "$124,440", "debt_11": "$124,440", "debt_12": "$124,440", "debt_1": "$124,440", "debt_2": "$328,377", "debt_3": "$395,336", "debt_4": "$458,608", "debt_5": "$521,880", "debt_6": "$575,152", "debt_7": "$638,424", "debt_8": "$638,424", "debt_fytd": "$(638,424)", "net_assets9": "(464,951)", "net_assets10": "(621,130)", "net_assets11": "(628,380)", "net_assets12": "(618,974)", "net_assets1": "(589,125)", "net_assets2": "(587,470)", "net_assets3": "(611,664)", "net_assets4": "(612,633)", "net_assets5": "(436,001)", "net_assets6": "(296,395)", "net_assets7": "(110,757)", "net_assets8": "(569,175)"}, {"Activity": "FA-AD", "Description": "Accumulated Depreciation", "Category": "Assets", "Subcategory": "Capital Assets, Net", "FYE": "(1,375,158)", "BS_id": 9, "school": "manara", "total_sum1": 0, "total_sum2": -203937.28, "total_sum3": -66959.07999999999, "total_sum4": -63272.0, "total_sum5": -63272.0, "total_sum6": -53272.0, "total_sum7": -63272.0, "total_sum8": 0, "total_sum9": -62219.82, "total_sum10": -62219.82, "total_sum11": 0, "total_sum12": 0}, {"Activity": "AP", "Description": "Accounts Payable", "Category": "Liabilities and Net Assets", "Subcategory": "Current Liabilities", "FYE": "220,425", "BS_id": 10, "school": "advantage", "total_sum1": -34876.22999999999, "total_sum2": 29311.689999999995, "total_sum3": 6161.090000000009, "total_sum4": -7009.190000000002, "total_sum5": 3490.809999999999, "total_sum6": 137.25999999999476, "total_sum7": 2050.970000000003, "total_sum8": 1330.149999999987, "total_sum9": 219302.29000000004, "total_sum10": 25783.669999999995, "total_sum11": 1970.2100000000116, "total_sum12": -629.2900000000081}, {"Activity": "AP", "Description": "Accounts Payable", "Category": "Liabilities and Net Assets", "Subcategory": "Current Liabilities", "FYE": "1,552,774", "BS_id": 10, "school": "cumberland", "total_sum1": -34876.22999999999, "total_sum2": 29311.689999999995, "total_sum3": 6161.090000000009, "total_sum4": -7009.190000000002, "total_sum5": 3490.809999999999, "total_sum6": 137.25999999999476, "total_sum7": 2050.970000000003, "total_sum8": 1330.149999999987, "total_sum9": 219302.29000000004, "total_sum10": 25783.669999999995, "total_sum11": 1970.2100000000116, "total_sum12": -629.2900000000081}, {"Activity": "AP", "Description": "Accounts Payable", "Category": "Liabilities and Net Assets", "Subcategory": "Current Liabilities", "FYE": "69,675", "BS_id": 10, "school": "prepschool", "total_sum1": -34876.22999999999, "total_sum2": 29311.689999999995, "total_sum3": 6161.090000000009, "total_sum4": -7009.190000000002, "total_sum5": 3490.809999999999, "total_sum6": 137.25999999999476, "total_sum7": 2050.970000000003, "total_sum8": 1330.149999999987, "total_sum9": 219302.29000000004, "total_sum10": 25783.669999999995, "total_sum11": 1970.2100000000116, "total_sum12": -629.2900000000081}, {"Activity": "AP", "Description": "Accounts Payable", "Category": "Liabilities and Net Assets", "Subcategory": "Current Liabilities", "FYE": "605,067", "BS_id": 10, "school": "village-tech", "total_sum1": -34876.22999999999, "total_sum2": 29311.689999999995, "total_sum3": 6161.090000000009, "total_sum4": -7009.190000000002, "total_sum5": 3490.809999999999, "total_sum6": 137.25999999999476, "total_sum7": 2050.970000000003, "total_sum8": 1330.149999999987, "total_sum9": 219302.29000000004, "total_sum10": 25783.669999999995, "total_sum11": 1970.2100000000116, "total_sum12": -629.2900000000081, "difference_9": "$824,369", "difference_10": "$850,153", "difference_11": "$852,123", "difference_12": "$851,494", "difference_1": "$816,618", "difference_2": "$845,929", "difference_3": "$852,090", "difference_4": "$845,081", "difference_5": "$848,572", "difference_6": "$848,709", "difference_7": "$850,760", "difference_8": "$852,090", "fytd": "$247,023", "debt_9": "$385,765", "debt_10": "$359,981", "debt_11": "$358,011", "debt_12": "$358,640", "debt_1": "$393,516", "debt_2": "$364,205", "debt_3": "$358,044", "debt_4": "$365,053", "debt_5": "$361,562", "debt_6": "$361,425", "debt_7": "$359,374", "debt_8": "$358,044", "debt_fytd": "$247,023", "net_assets9": "140,116", "net_assets10": "(16,063)", "net_assets11": "(23,313)", "net_assets12": "(13,907)", "net_assets1": "15,942", "net_assets2": "17,597", "net_assets3": "(6,597)", "net_assets4": "(7,566)", "net_assets5": "169,066", "net_assets6": "308,672", "net_assets7": "494,310", "net_assets8": "35,892"}, {"Activity": "AP", "Description": "Accounts Payable", "Category": "Liabilities and Net Assets", "Subcategory": "Current Liabilities", "FYE": "241,596", "BS_id": 10, "school": "manara", "total_sum1": -34876.22999999999, "total_sum2": 29311.689999999995, "total_sum3": 6161.090000000009, "total_sum4": -7009.190000000002, "total_sum5": 3490.809999999999, "total_sum6": 137.25999999999476, "total_sum7": 2050.970000000003, "total_sum8": 1330.149999999987, "total_sum9": 219302.29000000004, "total_sum10": 25783.669999999995, "total_sum11": 1970.2100000000116, "total_sum12": -629.2900000000081}, {"Activity": "Acc-Exp", "Description": "Accrued Expenses", "Category": "Liabilities and Net Assets", "Subcategory": "Current Liabilities", "FYE": "730,073", "BS_id": 11, "school": "advantage", "total_sum1": 57823.34000000012, "total_sum2": -52961.13999999981, "total_sum3": -33476.79999999974, "total_sum4": -15498.06999999986, "total_sum5": 24874.11000000004, "total_sum6": -87861.15999999983, "total_sum7": -24478.95999999991, "total_sum8": 63306.66000000003, "total_sum9": 75282.41999999947, "total_sum10": 57625.44000000013, "total_sum11": 85202.13000000028, "total_sum12": -127043.90000000013}, {"Activity": "Acc-Exp", "Description": "Accrued Expenses", "Category": "Liabilities and Net Assets", "Subcategory": "Current Liabilities", "FYE": "730,070", "BS_id": 11, "school": "cumberland", "total_sum1": 57823.34000000012, "total_sum2": -52961.13999999981, "total_sum3": -33476.79999999974, "total_sum4": -15498.06999999986, "total_sum5": 24874.11000000004, "total_sum6": -87861.15999999983, "total_sum7": -24478.95999999991, "total_sum8": 63306.66000000003, "total_sum9": 75282.41999999947, "total_sum10": 57625.44000000013, "total_sum11": 85202.13000000028, "total_sum12": -127043.90000000013}, {"Activity": "Acc-Exp", "Description": "Accrued Expenses", "Category": "Liabilities and Net Assets", "Subcategory": "Current Liabilities", "FYE": "10,982", "BS_id": 11, "school": "prepschool", "total_sum1": 57823.34000000012, "total_sum2": -52961.13999999981, "total_sum3": -33476.79999999974, "total_sum4": -15498.06999999986, "total_sum5": 24874.11000000004, "total_sum6": -87861.15999999983, "total_sum7": -24478.95999999991, "total_sum8": 63306.66000000003, "total_sum9": 75282.41999999947, "total_sum10": 57625.44000000013, "total_sum11": 85202.13000000028, "total_sum12": -127043.90000000013}, {"Activity": "Acc-Exp", "Description": "Accrued Expenses", "Category": "Liabilities and Net Assets", "Subcategory": "Current Liabilities", "FYE": "468,381", "BS_id": 11, "school": "village-tech", "total_sum1": 57823.34000000012, "total_sum2": -52961.13999999981, "total_sum3": -33476.79999999974, "total_sum4": -15498.06999999986, "total_sum5": 24874.11000000004, "total_sum6": -87861.15999999983, "total_sum7": -24478.95999999991, "total_sum8": 63306.66000000003, "total_sum9": 75282.41999999947, "total_sum10": 57625.44000000013, "total_sum11": 85202.13000000028, "total_sum12": -127043.90000000013, "difference_9": "$543,663", "difference_10": "$601,289", "difference_11": "$686,491", "difference_12": "$559,447", "difference_1": "$617,270", "difference_2": "$564,309", "difference_3": "$530,832", "difference_4": "$515,334", "difference_5": "$540,209", "difference_6": "$452,347", "difference_7": "$427,868", "difference_8": "$491,175", "fytd": "$22,794", "debt_9": "$393,099", "debt_10": "$335,473", "debt_11": "$250,271", "debt_12": "$377,315", "debt_1": "$319,492", "debt_2": "$372,453", "debt_3": "$405,930", "debt_4": "$421,428", "debt_5": "$396,553", "debt_6": "$484,415", "debt_7": "$508,894", "debt_8": "$445,587", "debt_fytd": "$22,794", "net_assets9": "3,430", "net_assets10": "(152,749)", "net_assets11": "(159,999)", "net_assets12": "(150,593)", "net_assets1": "(120,744)", "net_assets2": "(119,089)", "net_assets3": "(143,283)", "net_assets4": "(144,252)", "net_assets5": "32,380", "net_assets6": "171,986", "net_assets7": "357,624", "net_assets8": "(100,794)"}, {"Activity": "Acc-Exp", "Description": "Accrued Expenses", "Category": "Liabilities and Net Assets", "Subcategory": "Current Liabilities", "FYE": "", "BS_id": 11, "school": "manara", "total_sum1": 57823.34000000012, "total_sum2": -52961.13999999981, "total_sum3": -33476.79999999974, "total_sum4": -15498.06999999986, "total_sum5": 24874.11000000004, "total_sum6": -87861.15999999983, "total_sum7": -24478.95999999991, "total_sum8": 63306.66000000003, "total_sum9": 75282.41999999947, "total_sum10": 57625.44000000013, "total_sum11": 85202.13000000028, "total_sum12": -127043.90000000013}, {"Activity": "OtherLiab", "Description": "Other Liabilities", "Category": "Liabilities and Net Assets", "Subcategory": "Current Liabilities", "FYE": "", "BS_id": 12, "school": "advantage", "total_sum1": 0, "total_sum2": 0, "total_sum3": 0, "total_sum4": 0, "total_sum5": 0, "total_sum6": 0, "total_sum7": 0, "total_sum8": 0, "total_sum9": 0, "total_sum10": 0, "total_sum11": 0, "total_sum12": 0}, {"Activity": "OtherLiab", "Description": "Other Liabilities", "Category": "Liabilities and Net Assets", "Subcategory": "Current Liabilities", "FYE": "856,031", "BS_id": 12, "school": "prepschool", "total_sum1": 0, "total_sum2": 0, "total_sum3": 0, "total_sum4": 0, "total_sum5": 0, "total_sum6": 0, "total_sum7": 0, "total_sum8": 0, "total_sum9": 0, "total_sum10": 0, "total_sum11": 0, "total_sum12": 0}, {"Activity": "OtherLiab", "Description": "Other Liabilities", "Category": "Liabilities and Net Assets", "Subcategory": "Current Liabilities", "FYE": "28,285", "BS_id": 12, "school": "cumberland", "total_sum1": 0, "total_sum2": 0, "total_sum3": 0, "total_sum4": 0, "total_sum5": 0, "total_sum6": 0, "total_sum7": 0, "total_sum8": 0, "total_sum9": 0, "total_sum10": 0, "total_sum11": 0, "total_sum12": 0}, {"Activity": "OtherLiab", "Description": "Other Liabilities", "Category": "Liabilities and Net Assets", "Subcategory": "Current Liabilities", "FYE": "", "BS_id": 12, "school": "village-tech", "total_sum1": 0, "total_sum2": 0, "total_sum3": 0, "total_sum4": 0, "total_sum5": 0, "total_sum6": 0, "total_sum7": 0, "total_sum8": 0, "total_sum9": 0, "total_sum10": 0, "total_sum11": 0, "total_sum12": 0, "difference_9": "", "difference_10": "", "difference_11": "", "difference_12": "", "difference_1": "", "difference_2": "", "difference_3": "", "difference_4": "", "difference_5": "", "difference_6": "", "difference_7": "", "difference_8": "", "fytd": "", "debt_9": "", "debt_10": "", "debt_11": "", "debt_12": "", "debt_1": "", "debt_2": "", "debt_3": "", "debt_4": "", "debt_5": "", "debt_6": "", "debt_7": "", "debt_8": "", "debt_fytd": "", "net_assets9": "(464,951)", "net_assets10": "(621,130)", "net_assets11": "(628,380)", "net_assets12": "(618,974)", "net_assets1": "(589,125)", "net_assets2": "(587,470)", "net_assets3": "(611,664)", "net_assets4": "(612,633)", "net_assets5": "(436,001)", "net_assets6": "(296,395)", "net_assets7": "(110,757)", "net_assets8": "(569,175)"}, {"Activity": "OtherLiab", "Description": "Other Liabilities", "Category": "Liabilities and Net Assets", "Subcategory": "Current Liabilities", "FYE": "484,322", "BS_id": 12, "school": "manara", "total_sum1": 0, "total_sum2": 0, "total_sum3": 0, "total_sum4": 0, "total_sum5": 0, "total_sum6": 0, "total_sum7": 0, "total_sum8": 0, "total_sum9": 0, "total_sum10": 0, "total_sum11": 0, "total_sum12": 0}, {"Activity": "Debt-C", "Description": "Deferred Revenue", "Category": "Liabilities and Net Assets", "Subcategory": "Current Liabilities", "FYE": "5,695", "BS_id": 13, "school": "advantage", "total_sum1": 0, "total_sum2": 0, "total_sum3": 0, "total_sum4": 0, "total_sum5": 0, "total_sum6": 0, "total_sum7": 0, "total_sum8": 0, "total_sum9": 0, "total_sum10": 0, "total_sum11": 0, "total_sum12": 0}, {"Activity": "Debt-C", "Description": "Deferred Revenue", "Category": "Liabilities and Net Assets", "Subcategory": "Current Liabilities", "FYE": "155,333", "BS_id": 13, "school": "prepschool", "total_sum1": 0, "total_sum2": 0, "total_sum3": 0, "total_sum4": 0, "total_sum5": 0, "total_sum6": 0, "total_sum7": 0, "total_sum8": 0, "total_sum9": 0, "total_sum10": 0, "total_sum11": 0, "total_sum12": 0}, {"Activity": "Debt-C", "Description": "Deferred Revenue", "Category": "Liabilities and Net Assets", "Subcategory": "Current Liabilities", "FYE": "", "BS_id": 13, "school": "cumberland", "total_sum1": 0, "total_sum2": 0, "total_sum3": 0, "total_sum4": 0, "total_sum5": 0, "total_sum6": 0, "total_sum7": 0, "total_sum8": 0, "total_sum9": 0, "total_sum10": 0, "total_sum11": 0, "total_sum12": 0}, {"Activity": "Debt-C", "Description": "Deferred Revenue", "Category": "Liabilities and Net Assets", "Subcategory": "Current Liabilities", "FYE": "", "BS_id": 13, "school": "village-tech", "total_sum1": 0, "total_sum2": 0, "total_sum3": 0, "total_sum4": 0, "total_sum5": 0, "total_sum6": 0, "total_sum7": 0, "total_sum8": 0, "total_sum9": 0, "total_sum10": 0, "total_sum11": 0, "total_sum12": 0, "difference_9": "", "difference_10": "", "difference_11": "", "difference_12": "", "difference_1": "", "difference_2": "", "difference_3": "", "difference_4": "", "difference_5": "", "difference_6": "", "difference_7": "", "difference_8": "", "fytd": "", "debt_9": "", "debt_10": "", "debt_11": "", "debt_12": "", "debt_1": "", "debt_2": "", "debt_3": "", "debt_4": "", "debt_5": "", "debt_6": "", "debt_7": "", "debt_8": "", "debt_fytd": "", "net_assets9": "(464,951)", "net_assets10": "(621,130)", "net_assets11": "(628,380)", "net_assets12": "(618,974)", "net_assets1": "(589,125)", "net_assets2": "(587,470)", "net_assets3": "(611,664)", "net_assets4": "(612,633)", "net_assets5": "(436,001)", "net_assets6": "(296,395)", "net_assets7": "(110,757)", "net_assets8": "(569,175)"}, {"Activity": "Debt-C", "Description": "Deferred Revenue", "Category": "Liabilities and Net Assets", "Subcategory": "Current Liabilities", "FYE": "", "BS_id": 13, "school": "manara", "total_sum1": 0, "total_sum2": 0, "total_sum3": 0, "total_sum4": 0, "total_sum5": 0, "total_sum6": 0, "total_sum7": 0, "total_sum8": 0, "total_sum9": 0, "total_sum10": 0, "total_sum11": 0, "total_sum12": 0}, {"Activity": "Debt-C", "Description": "Accrued Interest", "Category": "Liabilities and Net Assets", "Subcategory": "Current Liabilities", "FYE": "40,552", "BS_id": 14, "school": "advantage", "total_sum1": 0, "total_sum2": 0, "total_sum3": 0, "total_sum4": 0, "total_sum5": 0, "total_sum6": 0, "total_sum7": 0, "total_sum8": 0, "total_sum9": 0, "total_sum10": 0, "total_sum11": 0, "total_sum12": 0}, {"Activity": "Debt-C", "Description": "Accrued Interest", "Category": "Liabilities and Net Assets", "Subcategory": "Current Liabilities", "FYE": "21,092", "BS_id": 14, "school": "prepschool", "total_sum1": 0, "total_sum2": 0, "total_sum3": 0, "total_sum4": 0, "total_sum5": 0, "total_sum6": 0, "total_sum7": 0, "total_sum8": 0, "total_sum9": 0, "total_sum10": 0, "total_sum11": 0, "total_sum12": 0}, {"Activity": "Debt-C", "Description": "Accrued Interest", "Category": "Liabilities and Net Assets", "Subcategory": "Current Liabilities", "FYE": "152,845", "BS_id": 14, "school": "cumberland", "total_sum1": 0, "total_sum2": 0, "total_sum3": 0, "total_sum4": 0, "total_sum5": 0, "total_sum6": 0, "total_sum7": 0, "total_sum8": 0, "total_sum9": 0, "total_sum10": 0, "total_sum11": 0, "total_sum12": 0}, {"Activity": "Debt-C", "Description": "Accrued Interest", "Category": "Liabilities and Net Assets", "Subcategory": "Current Liabilities", "FYE": "63,831", "BS_id": 14, "school": "village-tech", "total_sum1": 0, "total_sum2": 0, "total_sum3": 0, "total_sum4": 0, "total_sum5": 0, "total_sum6": 0, "total_sum7": 0, "total_sum8": 0, "total_sum9": 0, "total_sum10": 0, "total_sum11": 0, "total_sum12": 0, "difference_9": "$63,831", "difference_10": "$63,831", "difference_11": "$63,831", "difference_12": "$63,831", "difference_1": "$63,831", "difference_2": "$63,831", "difference_3": "$63,831", "difference_4": "$63,831", "difference_5": "$63,831", "difference_6": "$63,831", "difference_7": "$63,831", "difference_8": "$63,831", "fytd": "", "debt_9": "$63,831", "debt_10": "$63,831", "debt_11": "$63,831", "debt_12": "$63,831", "debt_1": "$63,831", "debt_2": "$63,831", "debt_3": "$63,831", "debt_4": "$63,831", "debt_5": "$63,831", "debt_6": "$63,831", "debt_7": "$63,831", "debt_8": "$63,831", "debt_fytd": "", "net_assets9": "(401,120)", "net_assets10": "(557,299)", "net_assets11": "(564,549)", "net_assets12": "(555,143)", "net_assets1": "(525,294)", "net_assets2": "(523,639)", "net_assets3": "(547,833)", "net_assets4": "(548,802)", "net_assets5": "(372,170)", "net_assets6": "(232,564)", "net_assets7": "(46,926)", "net_assets8": "(505,344)"}, {"Activity": "Debt-C", "Description": "Accrued Interest", "Category": "Liabilities and Net Assets", "Subcategory": "Current Liabilities", "FYE": "", "BS_id": 14, "school": "manara", "total_sum1": 0, "total_sum2": 0, "total_sum3": 0, "total_sum4": 0, "total_sum5": 0, "total_sum6": 0, "total_sum7": 0, "total_sum8": 0, "total_sum9": 0, "total_sum10": 0, "total_sum11": 0, "total_sum12": 0}, {"Activity": "Debt-C", "Description": "Current portion LTD", "Category": "Liabilities and Net Assets", "Subcategory": "Current Liabilities", "FYE": "755,000", "BS_id": 15, "school": "advantage", "total_sum1": 0, "total_sum2": 0, "total_sum3": 0, "total_sum4": 0, "total_sum5": 0, "total_sum6": 0, "total_sum7": 0, "total_sum8": 0, "total_sum9": 0, "total_sum10": 0, "total_sum11": 0, "total_sum12": 0}, {"Activity": "Debt-C", "Description": "Current portion LTD", "Category": "Liabilities and Net Assets", "Subcategory": "Current Liabilities", "FYE": "354,078", "BS_id": 15, "school": "village-tech", "total_sum1": 0, "total_sum2": 0, "total_sum3": 0, "total_sum4": 0, "total_sum5": 0, "total_sum6": 0, "total_sum7": 0, "total_sum8": 0, "total_sum9": 0, "total_sum10": 0, "total_sum11": 0, "total_sum12": 0, "difference_9": "$354,078", "difference_10": "$354,078", "difference_11": "$354,078", "difference_12": "$354,078", "difference_1": "$354,078", "difference_2": "$354,078", "difference_3": "$354,078", "difference_4": "$354,078", "difference_5": "$354,078", "difference_6": "$354,078", "difference_7": "$354,078", "difference_8": "$354,078", "fytd": "", "debt_9": "$354,078", "debt_10": "$354,078", "debt_11": "$354,078", "debt_12": "$354,078", "debt_1": "$354,078", "debt_2": "$354,078", "debt_3": "$354,078", "debt_4": "$354,078", "debt_5": "$354,078", "debt_6": "$354,078", "debt_7": "$354,078", "debt_8": "$354,078", "debt_fytd": "", "net_assets9": "(110,873)", "net_assets10": "(267,052)", "net_assets11": "(274,302)", "net_assets12": "(264,896)", "net_assets1": "(235,047)", "net_assets2": "(233,392)", "net_assets3": "(257,586)", "net_assets4": "(258,555)", "net_assets5": "(81,923)", "net_assets6": "57,683", "net_assets7": "243,321", "net_assets8": "(215,097)"}, {"Activity": "Debt-C", "Description": "Current portion LTD", "Category": "Liabilities and Net Assets", "Subcategory": "Current Liabilities", "FYE": "440,715", "BS_id": 15, "school": "prepschool", "total_sum1": 0, "total_sum2": 0, "total_sum3": 0, "total_sum4": 0, "total_sum5": 0, "total_sum6": 0, "total_sum7": 0, "total_sum8": 0, "total_sum9": 0, "total_sum10": 0, "total_sum11": 0, "total_sum12": 0}, {"Activity": "Debt-C", "Description": "Current portion LTD", "Category": "Liabilities and Net Assets", "Subcategory": "Current Liabilities", "FYE": "354,078", "BS_id": 15, "school": "village-tech", "total_sum1": 0, "total_sum2": 0, "total_sum3": 0, "total_sum4": 0, "total_sum5": 0, "total_sum6": 0, "total_sum7": 0, "total_sum8": 0, "total_sum9": 0, "total_sum10": 0, "total_sum11": 0, "total_sum12": 0, "difference_9": "$354,078", "difference_10": "$354,078", "difference_11": "$354,078", "difference_12": "$354,078", "difference_1": "$354,078", "difference_2": "$354,078", "difference_3": "$354,078", "difference_4": "$354,078", "difference_5": "$354,078", "difference_6": "$354,078", "difference_7": "$354,078", "difference_8": "$354,078", "fytd": "", "debt_9": "$354,078", "debt_10": "$354,078", "debt_11": "$354,078", "debt_12": "$354,078", "debt_1": "$354,078", "debt_2": "$354,078", "debt_3": "$354,078", "debt_4": "$354,078", "debt_5": "$354,078", "debt_6": "$354,078", "debt_7": "$354,078", "debt_8": "$354,078", "debt_fytd": "", "net_assets9": "(110,873)", "net_assets10": "(267,052)", "net_assets11": "(274,302)", "net_assets12": "(264,896)", "net_assets1": "(235,047)", "net_assets2": "(233,392)", "net_assets3": "(257,586)", "net_assets4": "(258,555)", "net_assets5": "(81,923)", "net_assets6": "57,683", "net_assets7": "243,321", "net_assets8": "(215,097)"}, {"Activity": "Debt-C", "Description": "Current portion LTD", "Category": "Liabilities and Net Assets", "Subcategory": "Current Liabilities", "FYE": "410,000", "BS_id": 15, "school": "cumberland", "total_sum1": 0, "total_sum2": 0, "total_sum3": 0, "total_sum4": 0, "total_sum5": 0, "total_sum6": 0, "total_sum7": 0, "total_sum8": 0, "total_sum9": 0, "total_sum10": 0, "total_sum11": 0, "total_sum12": 0}, {"Activity": "Debt-C", "Description": "Current portion LTD", "Category": "Liabilities and Net Assets", "Subcategory": "Current Liabilities", "FYE": "509,786", "BS_id": 15, "school": "manara", "total_sum1": 0, "total_sum2": 0, "total_sum3": 0, "total_sum4": 0, "total_sum5": 0, "total_sum6": 0, "total_sum7": 0, "total_sum8": 0, "total_sum9": 0, "total_sum10": 0, "total_sum11": 0, "total_sum12": 0}, {"Activity": "LTD", "Description": "Loan Payable, Net of Issuance Costs", "Category": "Debt", "Subcategory": "Long Term Debt", "FYE": "21,328,569", "BS_id": 16, "school": "advantage", "total_sum1": 0, "total_sum2": 0, "total_sum3": 0, "total_sum4": 0, "total_sum5": -9945.0, "total_sum6": -1105.0, "total_sum7": 0, "total_sum8": 0, "total_sum9": 0, "total_sum10": 0, "total_sum11": 0, "total_sum12": 0}, {"Activity": "LTD", "Description": "Loan Payable, Net of Issuance Costs", "Category": "Debt", "Subcategory": "Long Term Debt", "FYE": "74,454,385", "BS_id": 16, "school": "cumberland", "total_sum1": 0, "total_sum2": 0, "total_sum3": 0, "total_sum4": 0, "total_sum5": -9945.0, "total_sum6": -1105.0, "total_sum7": 0, "total_sum8": 0, "total_sum9": 0, "total_sum10": 0, "total_sum11": 0, "total_sum12": 0}, {"Activity": "LTD", "Description": "Loan Payable, Net of Issuance Costs", "Category": "Debt", "Subcategory": "Long Term Debt", "FYE": "25,965,441", "BS_id": 16, "school": "village-tech", "total_sum1": 0, "total_sum2": 0, "total_sum3": 0, "total_sum4": 0, "total_sum5": -9945.0, "total_sum6": -1105.0, "total_sum7": 0, "total_sum8": 0, "total_sum9": 0, "total_sum10": 0, "total_sum11": 0, "total_sum12": 0, "difference_9": "$25,965,441", "difference_10": "$25,965,441", "difference_11": "$25,965,441", "difference_12": "$25,965,441", "difference_1": "$25,965,441", "difference_2": "$25,965,441", "difference_3": "$25,965,441", "difference_4": "$25,965,441", "difference_5": "$25,955,496", "difference_6": "$25,954,391", "difference_7": "$25,954,391", "difference_8": "$25,954,391", "fytd": "$(11,050)", "debt_9": "$25,965,441", "debt_10": "$25,965,441", "debt_11": "$25,965,441", "debt_12": "$25,965,441", "debt_1": "$25,965,441", "debt_2": "$25,965,441", "debt_3": "$25,965,441", "debt_4": "$25,965,441", "debt_5": "$25,975,386", "debt_6": "$25,976,491", "debt_7": "$25,976,491", "debt_8": "$25,976,491", "debt_fytd": "$(11,050)", "net_assets9": "25,500,490", "net_assets10": "25,344,311", "net_assets11": "25,337,061", "net_assets12": "25,346,467", "net_assets1": "25,376,316", "net_assets2": "25,377,971", "net_assets3": "25,353,777", "net_assets4": "25,352,808", "net_assets5": "25,529,440", "net_assets6": "25,669,046", "net_assets7": "25,854,684", "net_assets8": "25,396,266"}, {"Activity": "LTD", "Description": "Loan Payable, Net of Issuance Costs", "Category": "Debt", "Subcategory": "Long Term Debt", "FYE": "", "BS_id": 16, "school": "manara", "total_sum1": 0, "total_sum2": 0, "total_sum3": 0, "total_sum4": 0, "total_sum5": -9945.0, "total_sum6": -1105.0, "total_sum7": 0, "total_sum8": 0, "total_sum9": 0, "total_sum10": 0, "total_sum11": 0, "total_sum12": 0}, {"Activity": "LTD", "Description": "Loan Payable, Net of Issuance Costs", "Category": "Debt", "Subcategory": "Long Term Debt", "FYE": "16,084,062", "BS_id": 16, "school": "prepschool", "total_sum1": 0, "total_sum2": 0, "total_sum3": 0, "total_sum4": 0, "total_sum5": -9945.0, "total_sum6": -1105.0, "total_sum7": 0, "total_sum8": 0, "total_sum9": 0, "total_sum10": 0, "total_sum11": 0, "total_sum12": 0}, {"Activity": "Equity", "Description": "", "Category": "Net Assets", "Subcategory": "", "FYE": "11,141,146", "BS_id": 17, "school": "advantage", "total_sum1": 0, "total_sum2": 0, "total_sum3": 0, "total_sum4": 0, "total_sum5": 0, "total_sum6": 0, "total_sum7": 0, "total_sum8": 0, "total_sum9": 0, "total_sum10": 0, "total_sum11": 0, "total_sum12": 0}, {"Activity": "Equity", "Description": "", "Category": "Net Assets", "Subcategory": "", "FYE": "15,059,123", "BS_id": 17, "school": "cumberland", "total_sum1": 0, "total_sum2": 0, "total_sum3": 0, "total_sum4": 0, "total_sum5": 0, "total_sum6": 0, "total_sum7": 0, "total_sum8": 0, "total_sum9": 0, "total_sum10": 0, "total_sum11": 0, "total_sum12": 0}, {"Activity": "Equity", "Description": "", "Category": "Net Assets", "Subcategory": "", "FYE": "4,594,412", "BS_id": 17, "school": "village-tech", "total_sum1": 0, "total_sum2": 0, "total_sum3": 0, "total_sum4": 0, "total_sum5": 0, "total_sum6": 0, "total_sum7": 0, "total_sum8": 0, "total_sum9": 0, "total_sum10": 0, "total_sum11": 0, "total_sum12": 0, "difference_9": "$4,594,412", "difference_10": "$4,594,412", "difference_11": "$4,594,412", "difference_12": "$4,594,412", "difference_1": "$4,594,412", "difference_2": "$4,594,412", "difference_3": "$4,594,412", "difference_4": "$4,594,412", "difference_5": "$4,594,412", "difference_6": "$4,594,412", "difference_7": "$4,594,412", "difference_8": "$4,594,412", "fytd": "", "debt_9": "$4,594,412", "debt_10": "$4,594,412", "debt_11": "$4,594,412", "debt_12": "$4,594,412", "debt_1": "$4,594,412", "debt_2": "$4,594,412", "debt_3": "$4,594,412", "debt_4": "$4,594,412", "debt_5": "$4,594,412", "debt_6": "$4,594,412", "debt_7": "$4,594,412", "debt_8": "$4,594,412", "debt_fytd": "", "net_assets9": "4,129,461", "net_assets10": "3,973,282", "net_assets11": "3,966,032", "net_assets12": "3,975,438", "net_assets1": "4,005,287", "net_assets2": "4,006,942", "net_assets3": "3,982,748", "net_assets4": "3,981,779", "net_assets5": "4,158,411", "net_assets6": "4,298,017", "net_assets7": "4,483,655", "net_assets8": "4,025,237"}, {"Activity": "Equity", "Description": "", "Category": "Net Assets", "Subcategory": "", "FYE": "4,545,609", "BS_id": 17, "school": "manara", "total_sum1": 0, "total_sum2": 0, "total_sum3": 0, "total_sum4": 0, "total_sum5": 0, "total_sum6": 0, "total_sum7": 0, "total_sum8": 0, "total_sum9": 0, "total_sum10": 0, "total_sum11": 0, "total_sum12": 0}, {"Activity": "Equity", "Description": "", "Category": "Net Assets", "Subcategory": "", "FYE": "6,771,073", "BS_id": 17, "school": "prepschool", "total_sum1": 0, "total_sum2": 0, "total_sum3": 0, "total_sum4": 0, "total_sum5": 0, "total_sum6": 0, "total_sum7": 0, "total_sum8": 0, "total_sum9": 0, "total_sum10": 0, "total_sum11": 0, "total_sum12": 0}]