[{"fund": "420", "obj": "5742", "description": "", "category": "Local Revenue", "value": "", "total_real1": "", "total_real2": "67,713", "total_real3": "31,871", "total_real4": "32,212", "total_real5": "205,470", "total_real6": "65,272", "total_real7": "68,180", "total_real8": "", "total_real9": "18,689", "total_real10": "14,736", "total_real11": "", "total_real12": "12,998"}, {"fund": "199", "obj": "5743", "description": "", "category": "Local Revenue", "value": "", "total_real1": "", "total_real2": "", "total_real3": "", "total_real4": "", "total_real5": "", "total_real6": "", "total_real7": "", "total_real8": "", "total_real9": "", "total_real10": "", "total_real11": "", "total_real12": ""}, {"fund": "199", "obj": "5744", "description": "Gifts", "category": "Local Revenue", "value": "", "total_real1": "", "total_real2": "", "total_real3": "", "total_real4": "", "total_real5": "", "total_real6": "", "total_real7": "", "total_real8": "", "total_real9": "", "total_real10": "", "total_real11": "", "total_real12": ""}, {"fund": "199", "obj": "5949", "description": "Adjustment", "category": "Local Revenue", "value": "", "total_real1": "", "total_real2": "", "total_real3": "", "total_real4": "", "total_real5": "", "total_real6": "", "total_real7": "", "total_real8": "", "total_real9": "", "total_real10": "", "total_real11": "", "total_real12": ""}, {"fund": "197", "obj": "5749", "description": "Senior Dues/Activity Funds", "category": "Local Revenue", "value": "", "total_real1": "", "total_real2": "", "total_real3": "", "total_real4": "", "total_real5": "", "total_real6": "", "total_real7": "", "total_real8": "", "total_real9": "", "total_real10": "", "total_real11": "", "total_real12": ""}, {"fund": "199", "obj": "5749", "description": "Senior Dues/Activity Funds", "category": "Local Revenue", "value": "", "total_real1": "", "total_real2": "", "total_real3": "", "total_real4": "", "total_real5": "", "total_real6": "", "total_real7": "", "total_real8": "", "total_real9": "", "total_real10": "", "total_real11": "", "total_real12": ""}, {"fund": "240", "obj": "5751", "description": "Athletics / Activity Funds", "category": "Local Revenue", "value": "", "total_real1": "", "total_real2": "390", "total_real3": "1,232", "total_real4": "363", "total_real5": "5", "total_real6": "99", "total_real7": "", "total_real8": "", "total_real9": "1,615", "total_real10": "541", "total_real11": "238", "total_real12": "389"}, {"fund": "461", "obj": "5752", "description": "Athletics / Activity Funds", "category": "Local Revenue", "value": "", "total_real1": "", "total_real2": "", "total_real3": "", "total_real4": "", "total_real5": "", "total_real6": "", "total_real7": "", "total_real8": "", "total_real9": "", "total_real10": "", "total_real11": "", "total_real12": ""}, {"fund": "199", "obj": "5753", "description": "Athletics / Activity Funds", "category": "Local Revenue", "value": "", "total_real1": "", "total_real2": "", "total_real3": "", "total_real4": "", "total_real5": "", "total_real6": "", "total_real7": "", "total_real8": "", "total_real9": "", "total_real10": "", "total_real11": "", "total_real12": ""}, {"fund": "199", "obj": "5759", "description": "Athletics / Activity Funds", "category": "Local Revenue", "value": "", "total_real1": "", "total_real2": "", "total_real3": "", "total_real4": "", "total_real5": "", "total_real6": "", "total_real7": "", "total_real8": "", "total_real9": "", "total_real10": "", "total_real11": "", "total_real12": ""}, {"fund": "461", "obj": "5759", "description": "Athletics / Activity Funds", "category": "Local Revenue", "value": "", "total_real1": "", "total_real2": "", "total_real3": "", "total_real4": "", "total_real5": "", "total_real6": "", "total_real7": "", "total_real8": "", "total_real9": "", "total_real10": "", "total_real11": "", "total_real12": ""}, {"fund": "865", "obj": "5759", "description": "Athletics / Activity Funds", "category": "Local Revenue", "value": "65,000", "total_real1": "", "total_real2": "", "total_real3": "", "total_real4": "", "total_real5": "", "total_real6": "", "total_real7": "", "total_real8": "", "total_real9": "", "total_real10": "", "total_real11": "", "total_real12": ""}, {"fund": "420", "obj": "5812", "description": "State FSP Revenue", "category": "State Program Revenue", "value": "11,897,303", "total_real1": "", "total_real2": "3,059,606", "total_real3": "1,473,447", "total_real4": "1,473,196", "total_real5": "1,488,570", "total_real6": "1,466,405", "total_real7": "1,466,442", "total_real8": "", "total_real9": "1,891,147", "total_real10": "1,482,693", "total_real11": "1,525,083", "total_real12": "1,529,840"}, {"fund": "420", "obj": "5811", "description": "State ASF Revenue", "category": "State Program Revenue", "value": "300,000", "total_real1": "", "total_real2": "216,054", "total_real3": "142,303", "total_real4": "81,520", "total_real5": "79,334", "total_real6": "150,348", "total_real7": "83,676", "total_real8": "", "total_real9": "94,634", "total_real10": "80,798", "total_real11": "81,881", "total_real12": "121,928"}, {"fund": "211", "obj": "5929", "description": "Title I, Part A & School Improvement", "category": "Federal Program Revenue", "value": "", "total_real1": "", "total_real2": "28,659", "total_real3": "", "total_real4": "", "total_real5": "", "total_real6": "114,530", "total_real7": "", "total_real8": "", "total_real9": "", "total_real10": "28,213", "total_real11": "29,105", "total_real12": "28,659"}, {"fund": "224", "obj": "5929", "description": "IDEA-B, Special Education", "category": "Federal Program Revenue", "value": "", "total_real1": "", "total_real2": "23,824", "total_real3": "", "total_real4": "", "total_real5": "", "total_real6": "94,635", "total_real7": "", "total_real8": "", "total_real9": "", "total_real10": "21,482", "total_real11": "24,185", "total_real12": "23,243"}, {"fund": "240", "obj": "5939", "description": "Child Nutrition", "category": "Federal Program Revenue", "value": "", "total_real1": "", "total_real2": "", "total_real3": "", "total_real4": "", "total_real5": "", "total_real6": "", "total_real7": "", "total_real8": "", "total_real9": "", "total_real10": "", "total_real11": "", "total_real12": ""}, {"fund": "240", "obj": "5921", "description": "", "category": "Federal Program Revenue", "value": "", "total_real1": "", "total_real2": "21,839", "total_real3": "12,744", "total_real4": "13,563", "total_real5": "15,179", "total_real6": "13,705", "total_real7": "", "total_real8": "", "total_real9": "", "total_real10": "", "total_real11": "29,032", "total_real12": "12,099"}, {"fund": "240", "obj": "5922", "description": "", "category": "Federal Program Revenue", "value": "", "total_real1": "", "total_real2": "97,001", "total_real3": "51,965", "total_real4": "54,446", "total_real5": "59,025", "total_real6": "57,014", "total_real7": "", "total_real8": "", "total_real9": "", "total_real10": "", "total_real11": "121,131", "total_real12": "49,925"}, {"fund": "240", "obj": "5929", "description": "", "category": "Federal Program Revenue", "value": "", "total_real1": "", "total_real2": "", "total_real3": "", "total_real4": "", "total_real5": "", "total_real6": "", "total_real7": "", "total_real8": "", "total_real9": "", "total_real10": "", "total_real11": "", "total_real12": ""}, {"fund": "225", "obj": "5929", "description": "", "category": "Federal Program Revenue", "value": "", "total_real1": "", "total_real2": "", "total_real3": "", "total_real4": "", "total_real5": "", "total_real6": "", "total_real7": "", "total_real8": "", "total_real9": "", "total_real10": "", "total_real11": "", "total_real12": ""}, {"fund": "255", "obj": "5929", "description": "Title II, Part A Supplementa", "category": "Federal Program Revenue", "value": "", "total_real1": "", "total_real2": "3,428", "total_real3": "", "total_real4": "", "total_real5": "", "total_real6": "17,299", "total_real7": "", "total_real8": "", "total_real9": "", "total_real10": "4,110", "total_real11": "3,859", "total_real12": "4,053"}, {"fund": "281", "obj": "5929", "description": "Prior Purchase Reimb. (PPRP)", "category": "Federal Program Revenue", "value": "", "total_real1": "", "total_real2": "", "total_real3": "", "total_real4": "", "total_real5": "", "total_real6": "446,281", "total_real7": "", "total_real8": "", "total_real9": "", "total_real10": "75,472", "total_real11": "77,835", "total_real12": "75,197"}, {"fund": "282", "obj": "5929", "description": "ESSER III", "category": "Federal Program Revenue", "value": "", "total_real1": "", "total_real2": "", "total_real3": "247,155", "total_real4": "", "total_real5": "", "total_real6": "857,992", "total_real7": "", "total_real8": "", "total_real9": "", "total_real10": "145,607", "total_real11": "169,384", "total_real12": "189,246"}, {"fund": "285", "obj": "5929", "description": "", "category": "Federal Program Revenue", "value": "", "total_real1": "", "total_real2": "", "total_real3": "", "total_real4": "", "total_real5": "", "total_real6": "", "total_real7": "", "total_real8": "", "total_real9": "", "total_real10": "", "total_real11": "", "total_real12": ""}, {"fund": "289", "obj": "5929", "description": "Title IV, Part A, Subpart 1", "category": "Federal Program Revenue", "value": "3,000,000", "total_real1": "", "total_real2": "1,453", "total_real3": "", "total_real4": "", "total_real5": "", "total_real6": "5,758", "total_real7": "", "total_real8": "", "total_real9": "", "total_real10": "1,431", "total_real11": "1,475", "total_real12": "1,453"}]